awesomest_search/__init__.py
awesomest_search/search.py
awesomest_search-0.3.0.dist-info/METADATA
awesomest_search-0.3.0.dist-info/WHEEL
awesomest_search-0.3.0.dist-info/top_level.txt
awesomest_search-0.3.0.dist-info/RECORD
