Metadata-Version: 2.1
Name: awesomest_search
Version: 0.3.0
Summary: Awesomest best fuzzy search
Home-page: https://github.com/prakHr/awesomest_search
Author: Prakhar Gandhi
Author-email: gprakhar0@gmail.com
Classifier: Programming Language :: Python :: 3
Classifier: License :: OSI Approved :: MIT License
Classifier: Operating System :: OS Independent
Requires-Python: >=3.6
Requires-Dist: mpire
